{"status":"done","chunks":{"main":[{"name":"main-2a3fed3f635de88c8faa.js","path":"C:\\Users\\Sarah\\PycharmProjects\\Aggregator\\articles\\static\\bundles\\main-2a3fed3f635de88c8faa.js"}]},"error":"ModuleBuildError","message":"Module build failed (from ./node_modules/babel-loader/lib/index.js):\nSyntaxError: C:/Users/Sarah/PycharmProjects/Aggregator/articles/static/js/index.js: Unexpected token, expected , (151:4)\n\n  149 | ReactDOM.render(\n  150 |     <ArticleList />\n> 151 |     window.react_mount\n      |     ^\n  152 | \n  153 | );\n"}